{"query":{"top":["vina24h","google","translate","www","google translate","cambodia","so xo","minh","youtube","xoso","facebook","vina","minh ngoc","vina24h com","minhngoc","vina24","vina24h com m","khmer lottery","you","weather","vina24h 2019","gmail","khmer24","khmer to english","livescore"],"rising":["coronavirus","xnxubd 2020 nvidia","vina24h 2020","vina24h com m 2020","អាកាសធាតុ","thinhnam net","អាកាសធាតុថ្ងៃស្អែក","xosonam","imls","live777","ag injector","thinhnam","thinh namnet","minhngocnet","joker388","vina 24 h","weather tomorrow","ming ngok","joker888","codashop","vina24h 2019 v","codashop cambodia","vina24h com/m download free","v24","google classroom"]},"entity":{"top":["XNXX - Website",".com - Top-level domain","Khmer language - Spoken language","Google - Technology company","Google Search - Topic","Translation - Topic","Film - Topic","Cambodia - Country in Asia","Lottery - Topic","Google Translate - Website","Number - Topic","YouTube - Video sharing company","Facebook - Social media service","Japan - Country in East Asia","Japanese Language - Spoken language","Facebook - Social media company","Japanese people - Ethnic group","English language - Spoken language","Thai people - People","Phnom Penh - Capital of Cambodia","Thai language - Spoken language","Meaning - Topic","Download - Topic","Khmer Lottery - Lottery shop in Phnom Penh, Cambodia"],"rising":["Coronavirus - Virus","V24 engine - Topic","Google Classroom - Topic","Net worth - Topic","Mobile Legends: Bang Bang - Mobile game","Weather - Topic","Pornhub - Website","Telegram - Software","Roblox - Online game","Lottery - Topic","Number - Topic","Twitter - Social networking service","WhatsApp - Mobile application","Minecraft - Topic","Skin - Topic","Death - Topic","Male - Topic","Minecraft - Video game","Computer Application - Software grouping","Portable Network Graphics - File format",".vn - Top-level domain","Meaning - Topic"]}}