{"query":{"top":["seznam","počasí","facebook","youtube","překladač","se","google","idos","idnes","prekladac","pocasi","email","centrum","you","seznam najdu tam","program tv","lidl","instagram","koronavirus","mapy","bazos","csfd","seznam najdu tam co neznám seznam seznam","seznam najdu tam co neznám seznam","seznam najdu tam co neznám"],"rising":["koronavirus","coronavirus","slunečná","iphone 11","koronavirus v česku","superstar 2020","počasí zítra","google classroom","mzcr","ministerstvo zdravotnictví","zalando lounge","seznam najdu tam co neznám přihlášení","about you","netflix","freefilm","zalando","karel gott","rohlik","zásilkovna","seznam zprávy","ct24","prehraj to","iprima","minecraft","dm software"]},"entity":{"top":["Seznam.cz - Marketing company","Weather - Topic","Prague - Capital of the Czech Republic","Google Translate - Website","Facebook - Social media service","Compiler - Topic","YouTube - Video sharing company","Facebook - Social media company",".cz - Top-level domain","Czechia - Country in Europe","Google - Technology company","Google Search - Topic","Brno - City in the Czech Republic","Online and offline - Topic","Film - Topic","Television - Topic","Map - Topic","Translation - Topic","Email - Topic","Recipe - Topic","Price - Topic","Child - Topic","Sales - Topic","Coronavirus - Virus","Czechs - Ethnic group"],"rising":["Coronavirus - Virus","About You - Company","Netflix - Production company","Minecraft - Video game","Minecraft - Topic","Pornhub - Website","Novinky.cz - Website"]}}