{"query":{"top":["facebook","youtube","translate","google","adjaranet","adjarabet","crystalbet","погода","google translate","amindi","mp3","liderbet","ამინდი","flashscore","crocobet","betlive","ok","myauto","instagram","odnoklassniki","europebet","kristal","you","saitebi","mymarket"],"rising":["coronavirus","stopcov","коронавирус","stopcov ge","mtavari arxi","sastiki stamboli","coronavirus statistics","worldometer","სასტიკი სტამბოლი","covid 19 statistics","ამინდი ხვალ","microsoft teams","teams","coronavirus update","brawl stars","stopcov.ge","sastiki stambuli qartulad","jokerstars","crystal","evropabeti","ამინდი","tavqariani","lms tsu","adjarasport","europa bet"]},"entity":{"top":["Facebook - Social media service",".ge - Top-level domain","Facebook - Social media company","Weather - Topic","Translation - Topic","YouTube - Video sharing company","Google - Technology company","Google Search - Topic","Tbilisi - Capital of Georgia","Film - Topic","Georgia - Country","Odnoklassniki - Social networking service","adjarabet - Company","Crystalbet - Casino in Tbilisi, Georgia","XNXX - Website","Download - Topic","Georgian language - Spoken language",".ru - Top-level domain","Google Translate - Website",".com - Top-level domain","Video - File format","MyAuto - Company in Tbilisi, Georgia","Russian Language - Spoken language","Batumi - City in Georgia","Online and offline - Topic"],"rising":["Coronavirus - Virus","Cubit - Topic","Brawl Stars - Mobile game","Virus - Infectious agent","Statistics - Discipline","İstanbul - City in Turkey","Canal - Topic","Microsoft Corporation - Technology company","General Electric - Multinational conglomerate company","Season - Topic","Pornhub - Website","Rico Credit - Topic","Yahoo! Mail - Topic","Weather - Topic","Russian ruble - Currency","Naruto - Manga series","Definition - Topic","Student - Topic","Email - Topic","Georgian language - Spoken language","Meaning - Topic"]}}