{"query":{"top":["guatemala","traductor","facebook","videos","whatsapp","youtube","google","imagenes","clima","whatsapp web","musica","gmail","ingles español","coronavirus","traductor ingles","sat","traductor ingles español","tiempo","juegos","mp3","barcelona","prensa libre","real madrid","traductor ingles a español","umg"],"rising":["coronavirus","coronavirus guatemala","coronavirus en guatemala","tiempo de mañana","blackboard umg","juegos de doodles de google populares","covid-19","tusa","sintomas del coronavirus","mi umg blackboard","zoom","iphone 11","tigo premios","semana santa 2020","geducar","classroom","alejandro giammattei","gobierno de guatemala","google classroom","whatsapp web","pelis plus","colplex","whatsapp plus","sat en linea","free fire"]},"entity":{"top":["Guatemala - Country in Central America","Translation - Topic","Guatemala City - Capital of Guatemala","Video - File format","Facebook - Social media service","Spanish Language - Spoken language","Spaniards - Ethnicity","Download - Topic","Image - Topic","Facebook - Social media company","English language - Spoken language","Google Search - Topic","Google - Technology company","YouTube - Video sharing company","WhatsApp - Mobile application","Woman - Topic","Lyrics - Topic","Music - Topic","Film - Topic","WhatsApp - Software developer","XNXX - Website","Game - Topic","Love - Topic","Child - Topic","Sentence - Linguistics"],"rising":["Coronavirus - Virus","Bond - Finance","Google Classroom - Topic","Morning - Topic","German language - Spoken language","Minecraft - Video game","Garena Free Fire - Mobile game","WhatsApp - Software developer","Minecraft - Topic","Web page - Topic","WhatsApp - Mobile application","Domicile - Law","Claro - Telecom company","Mile - Unit of length","Pollo Campero - Fast food restaurant company","Mariano Gálvez University of Guatemala - University in Guatemala City, Guatemala","Family - Topic","Symptom - Topic","Pornhub - Website","Millicom International Cellular S.A. - Telecommunications company","Web portal - Topic","Netflix - Production company","Pharmacy - Topic","Online and offline - Topic"]}}