{"query":{"top":["หนัง","royal","แปล","youtube","เพลง","google","facebook","แปล ภาษา","ผล บอล","translate","บ้าน บอล","บอล สด","www","สภาพ อากาศ","laos","xx","คอร์ด เพลง","mp3","you","xxxx","xsmb","ดู บอล","บอล วัน นี้","whatsapp","บ้าน ผล บอล"],"rising":["coronavirus","สล็อต 666","การ รายงาน ผล พรีเมียร์ ลีก","อากาศ พรุ่งนี้","ສະພາບອາກາດ","ເຕີມເກມ free fire","royal777","สล็อต 777","roya","6666","สภาพ อากาศ","เกม เชี","manager login","facebook apk","เตี ม เกม ฟี ฟาย","777","gg dịch","สล็อต","gclub168","เตี ม เกม","google classroom","เกม สล็อต","谷歌 翻译","bmw","หนัง netflix"]},"entity":{"top":["Film - Topic","XNXX - Website","Thai language - Spoken language","Thai people - People","Thailand - Country in Asia","Football - Sport","Translation - Topic",".com - Top-level domain","Japan - Country in East Asia","Japanese Language - Spoken language","YouTube - Video sharing company","Song - Composition type","Japanese people - Ethnic group","Laos - Country in Asia","Language - Field of study","Facebook - Social media service","Google - Technology company","Day - Unit of time","English language - Spoken language","Google Search - Topic","House - Topic","Lao language - Spoken language","Google Translate - Website","Online and offline - Topic","Price - Topic"],"rising":["Climate - Topic","Slot machine - Topic","Castlemaine XXXX - Topic","Pornhub - Website","BMW Motorrad - Topic","BMW - Automobile make","Bayerische Motoren Werke AG - Luxury vehicles company","Weather - Topic","Marketing - Field of study","Loan - Topic","Casino - Topic","Lawyer - Occupation","Company - Organization type","Home - Building use","WhatsApp - Mobile application","WhatsApp - Software developer","Sales - Topic","Manga - Art form","London - Capital of England","Insurance - Topic"]}}