{"query":{"top":["mauritius","facebook","youtube","google","translate","mp3","livescore","liverpool","defimedia","lexpress","quotes","mcb","coronavirus","meteo","defi","weather","premier league","google translate","mp3 juice","le defi","english to french","manchester united","flashscore","instagram","traduction"],"rising":["coronavirus","coronavirus update","coronavirus mauritius","worldometer","besafemoris","sushant singh rajput","www.mra.mu form","worldometer coronavirus","aston villa vs liverpool","google classroom","wazaa fm","www.mra.mu","weather tomorrow","man united vs man. city","hdss","mra.mu","coin master free spins","fudz","liverpool vs man united","myt money","premier league standings","meteo mauritius cyclone","whatsapp web","mra","galaxy.mu"]},"entity":{"top":["Mauritius - Country in East Africa","Meaning - Topic","Definition - Topic","Facebook - Social media service","Film - Topic","Facebook - Social media company","Translation - Topic","Le Défi Plus - Newspaper","French language - Spoken language","YouTube - Video sharing company","English language - Spoken language","French people - Ethnic group","Google - Technology company","Google Search - Topic","France - Country in Europe","News - Broadcast genre","XNXX - Website","L'Express - Mauritius","Video - File format","Download - Topic","Quotation - Literary genre","Liverpool F.C. - Football club",".com - Top-level domain","Manchester United F.C. - Football club","Meteorology - Field of study"],"rising":["Coronavirus - Virus","Virus - Infectious agent","Mauritius Revenue Authority - Government ministry","Employment - Topic","Election - Topic","Radio Plus - Mauritius","Netflix - Production company","Payment - Topic","Le Mauricien - Newspaper","Le Défi Plus - Newspaper","Bet365 - Company","WhatsApp - Software developer","China - Country in East Asia","Death - Topic","Symptom - Topic"]}}