{"query":{"top":["download","mp3","videos","news","betpawa","music","facebook","betway","youtube","google","tubidy","yo maps","epl","chelsea","premier league","zambia jobs","zambian music","whatsapp","weather","watchdog","waptrick","games","coronavirus","gsb","game"],"rising":["coronavirus","seer 1","coronavirus update","coronavirus in zambia","zamfund","myzamfund","cdn-af.feednews.com","mp3 paw","gt2.redirector.opera.com","weather tomorrow","mp3paw","facebooklogin","koswe","castlebet lite","y celeb","livescore.mobi","premier league standings","zoom","futaa","flashscore live","castlebet","google classroom","fz movies","ecz portal","mp3juice"]},"entity":{"top":["Zambia - Country in East Africa","MP3 - Format","Music download - Media format","Download - Topic","Video - File format",".com - Top-level domain","Song - Composition type","Meaning - Topic","Definition - Topic","News - Broadcast genre","Facebook - Social media service","Music - Topic","Facebook - Social media company","Film - Topic","Google - Technology company","Lyrics - Topic","Google Search - Topic","XNXX - Website","Premier League - Football league","Betway - Gambling company","Sports league - Topic","Woman - Topic","YouTube - Video sharing company","Africa - Continent","Girl - Topic"],"rising":["Coronavirus - Virus","Joeboy - Topic","Virus - Infectious agent","Chef 187 - Musician","Betway - Gambling company","Chef - Topic","Dollar - Topic","Justin Bieber - Canadian singer-songwriter","United States Dollar - Currency","Examinations Council of Zambia - Topic",".mobi - Top-level domain","Season - Topic","Bolabet Sports Betting- Downtown - Topic","Zambian kwacha - Currency"]}}